easydatejiakai/__init__.py
easydatejiakai/functions.py
easydatejiakai-0.1.0.dist-info/LICENSE
easydatejiakai-0.1.0.dist-info/METADATA
easydatejiakai-0.1.0.dist-info/WHEEL
easydatejiakai-0.1.0.dist-info/top_level.txt
easydatejiakai-0.1.0.dist-info/RECORD
