Metadata-Version: 2.1
Name: easydatejiakai
Version: 0.1.0
Summary: A simple package for date and time operations
Home-page: http://github.com/real-jiakai/easydate
Author: Jiakai
Author-email: gujiakai28@gmail.com
License: MIT
Classifier: Development Status :: 3 - Alpha
Classifier: Intended Audience :: Developers
Classifier: Natural Language :: English
Classifier: License :: OSI Approved :: MIT License
Classifier: Programming Language :: Python :: 3
Classifier: Programming Language :: Python :: 3.6
Classifier: Programming Language :: Python :: 3.7
Classifier: Programming Language :: Python :: 3.8
Requires-Python: >=3.6
License-File: LICENSE
